<marc:record>
<marc:leader>03077cam a2200577 a 4500</marc:leader>
<marc:controlfield tag="001">341405</marc:controlfield>
<marc:controlfield tag="005">20130221171832.0</marc:controlfield>
<marc:controlfield tag="008">860225s1774    enk           00000 eng d</marc:controlfield>
<marc:datafield ind1=" " ind2=" " tag="035">
<marc:subfield code="a">(PUVoyagerBIBID)186979</marc:subfield>
</marc:datafield>
<marc:datafield ind1=" " ind2=" " tag="035">
<marc:subfield code="a">(CStRLIN)PAUG86-B7658</marc:subfield>
</marc:datafield>
<marc:datafield ind1=" " ind2=" " tag="035">
<marc:subfield code="a">(MediadbVoyBIBID)341405</marc:subfield>
</marc:datafield>
<marc:datafield ind1=" " ind2=" " tag="035">
<marc:subfield code="9">ABB0260</marc:subfield>
</marc:datafield>
<marc:datafield ind1=" " ind2=" " tag="035">
<marc:subfield code="a">(END)sm_pr3991_a1_e38_1774_v1</marc:subfield>
</marc:datafield>
<marc:datafield ind1=" " ind2=" " tag="035">
<marc:subfield code="a">(END)sm_pr3991_a1_e38_1774_v2</marc:subfield>
</marc:datafield>
<marc:datafield ind1=" " ind2=" " tag="040">
<marc:subfield code="a">PU</marc:subfield>
<marc:subfield code="c">PU</marc:subfield>
</marc:datafield>
<marc:datafield ind1=" " ind2=" " tag="090">
<marc:subfield code="a">PR3991.A1</marc:subfield>
<marc:subfield code="b">E38 1774</marc:subfield>
<marc:subfield code="i">02/25/86 CTZ</marc:subfield>
</marc:datafield>
<marc:datafield ind1="0" ind2="0" tag="245">
<marc:subfield code="a">Edward :</marc:subfield>
<marc:subfield code="b">a novel : in two volumes.</marc:subfield>
</marc:datafield>
<marc:datafield ind1=" " ind2=" " tag="246">
<marc:subfield code="a">Edward. A novel. In two volumes. Dedicated (by permission) to her majesty. Vol. I.</marc:subfield>
<marc:subfield code="d">Letter-press</marc:subfield>
<marc:subfield code="x">Volume</marc:subfield>
<marc:subfield code="g">Full</marc:subfield>
<marc:subfield code="v">v.1</marc:subfield>
</marc:datafield>
<marc:datafield ind1=" " ind2=" " tag="246">
<marc:subfield code="a">Edward. A novel.</marc:subfield>
<marc:subfield code="d">Letter-press</marc:subfield>
<marc:subfield code="x">Work</marc:subfield>
<marc:subfield code="g">Half</marc:subfield>
<marc:subfield code="v">v.1</marc:subfield>
<marc:subfield code="v">v.2</marc:subfield>
</marc:datafield>
<marc:datafield ind1=" " ind2=" " tag="246">
<marc:subfield code="a">Edward. A novel. In two volumes. Dedicated (by permission) to her majesty. Vol. II.</marc:subfield>
<marc:subfield code="d">Letter-press</marc:subfield>
<marc:subfield code="x">Volume</marc:subfield>
<marc:subfield code="g">Full</marc:subfield>
<marc:subfield code="v">v.2</marc:subfield>
</marc:datafield>
<marc:datafield ind1="0" ind2="7" tag="246">
<marc:subfield code="a">Edward. A novel.</marc:subfield>
<marc:subfield code="v">v.1</marc:subfield>
<marc:subfield code="v">v.2</marc:subfield>
</marc:datafield>
<marc:datafield ind1=" " ind2=" " tag="260">
<marc:subfield code="a">London</marc:subfield>
<marc:subfield code="b">London: Printed for T. Davies, Russell-Street, Covent-Garden; bookseller to the Royal Academy.</marc:subfield>
<marc:subfield code="c">M.DCC.LXXIV.</marc:subfield>
<marc:subfield code="v">v.1</marc:subfield>
<marc:subfield code="v">v.2</marc:subfield>
<marc:subfield code="a">[London]</marc:subfield>
</marc:datafield>
<marc:datafield ind1=" " ind2=" " tag="300">
<marc:subfield code="a">2 v. ;</marc:subfield>
<marc:subfield code="c">18 cm. (12mo)</marc:subfield>
<marc:subfield code="x">Duodecimo</marc:subfield>
<marc:subfield code="x">In two volumes.</marc:subfield>
<marc:subfield code="a">[2 v.]</marc:subfield>
</marc:datafield>
<marc:datafield ind1="4" ind2=" " tag="510">
<marc:subfield code="a">ESTC (RLIN)</marc:subfield>
<marc:subfield code="c">T70086</marc:subfield>
</marc:datafield>
<marc:datafield ind1="4" ind2=" " tag="510">
<marc:subfield code="a">English novel, 1770-1829,</marc:subfield>
<marc:subfield code="c">1774:6</marc:subfield>
</marc:datafield>
<marc:datafield ind1="4" ind2=" " tag="510">
<marc:subfield code="a">Block, A.  Engl. novel (1961 ed.),</marc:subfield>
<marc:subfield code="c">p.66</marc:subfield>
</marc:datafield>
<marc:datafield ind1=" " ind2=" " tag="520">
<marc:subfield code="a">Dedication</marc:subfield>
<marc:subfield code="b">To the queen.</marc:subfield>
<marc:subfield code="c">Front</marc:subfield>
<marc:subfield code="v">v.1</marc:subfield>
<marc:subfield code="x">""As your majesty is acquainted with the motives which first induced me to publish this little production...""</marc:subfield>
<marc:subfield code="x">Running title for this section is ""Dedication.""</marc:subfield>
<marc:subfield code="x">Signed ""Madam, your majesty's most devoted and obedient humble servant, the author."</marc:subfield>
</marc:datafield>
<marc:datafield ind1=" " ind2=" " tag="520">
<marc:subfield code="a">Errata</marc:subfield>
<marc:subfield code="b">Errata in Vol. I.</marc:subfield>
<marc:subfield code="c">Front</marc:subfield>
<marc:subfield code="v">v.1</marc:subfield>
</marc:datafield>
<marc:datafield ind1=" " ind2=" " tag="592">
<marc:subfield code="a">Epistolary</marc:subfield>
</marc:datafield>
<marc:datafield ind1=" " ind2=" " tag="594">
<marc:subfield code="a">Lady Bateman 2 vol:</marc:subfield>
<marc:subfield code="b">Ink</marc:subfield>
<marc:subfield code="v">v.1</marc:subfield>
<marc:subfield code="v">v.2</marc:subfield>
<marc:subfield code="x">On recto of front free endpaper</marc:subfield>
</marc:datafield>
<marc:datafield ind1=" " ind2=" " tag="599">
<marc:subfield code="a">Author (text)</marc:subfield>
<marc:subfield code="b">Generic/Descriptive</marc:subfield>
<marc:subfield code="2">Madam, your majesty's most devoted and obedient humble servant, the author.</marc:subfield>
<marc:subfield code="3">Letter</marc:subfield>
<marc:subfield code="5">Indeterminate</marc:subfield>
<marc:subfield code="6">Unknown</marc:subfield>
</marc:datafield>
<marc:datafield ind1=" " ind2="7" tag="656">
<marc:subfield code="a">Epistolary fiction</marc:subfield>
<marc:subfield code="z">England</marc:subfield>
<marc:subfield code="y">18th century</marc:subfield>
<marc:subfield code="2">rbgenr</marc:subfield>
</marc:datafield>
<marc:datafield ind1=" " ind2="4" tag="650">
<marc:subfield code="a">CHR 1774</marc:subfield>
</marc:datafield>
<marc:datafield ind1=" " ind2="4" tag="650">
<marc:subfield code="a">PRO Singer, Jacob (donor)</marc:subfield>
</marc:datafield>
<marc:datafield ind1=" " ind2="4" tag="650">
<marc:subfield code="a">PRO Singer, Leah (donor)</marc:subfield>
</marc:datafield>
<marc:datafield ind1=" " ind2="4" tag="650">
<marc:subfield code="a">PRO Singer, Godfrey F. (honoree)</marc:subfield>
</marc:datafield>
<marc:datafield ind1=" " ind2="4" tag="650">
<marc:subfield code="a">PRO Bateman, Lady (autograph)</marc:subfield>
</marc:datafield>
<marc:datafield ind1=" " ind2=" " tag="700">
<marc:subfield code="a">Bateman, Elizabeth Bateman Viscountess</marc:subfield>
<marc:subfield code="d">d. 1802</marc:subfield>
<marc:subfield code="4">Inscribed name</marc:subfield>
<marc:subfield code="5">Authorized</marc:subfield>
</marc:datafield>
<marc:datafield ind1=" " ind2=" " tag="700">
<marc:subfield code="a">Davies, Thomas</marc:subfield>
<marc:subfield code="d">1713-1785</marc:subfield>
<marc:subfield code="4">Printed for</marc:subfield>
<marc:subfield code="5">Authorized</marc:subfield>
</marc:datafield>
<marc:datafield ind1=" " ind2=" " tag="700">
<marc:subfield code="a">Charlotte, Queen, consort of George III, King of Great Britain</marc:subfield>
<marc:subfield code="d">1744-1818</marc:subfield>
<marc:subfield code="4">Dedicatee</marc:subfield>
<marc:subfield code="5">Authorized</marc:subfield>
</marc:datafield>
<marc:datafield ind1=" " ind2=" " tag="710">
<marc:subfield code="a">T. Davies</marc:subfield>
<marc:subfield code="4">Printed for</marc:subfield>
<marc:subfield code="5">Unauthorized</marc:subfield>
</marc:datafield>
<marc:datafield ind1="2" ind2=" " tag="710">
<marc:subfield code="a">Collection of British and American Fiction, 1660-1830 (University of Pennsylvania)</marc:subfield>
</marc:datafield>
<marc:datafield ind1="2" ind2=" " tag="710">
<marc:subfield code="a">Early Novels</marc:subfield>
<marc:subfield code="5">University of Pennsylvania</marc:subfield>
</marc:datafield>
<marc:datafield ind1=" " ind2=" " tag="752">
<marc:subfield code="a">England</marc:subfield>
<marc:subfield code="d">London.</marc:subfield>
</marc:datafield>
<marc:datafield ind1="0" ind2="1" tag="852">
<marc:subfield code="b">scsing</marc:subfield>
<marc:subfield code="t">1</marc:subfield>
<marc:subfield code="h">PR3991.A1</marc:subfield>
<marc:subfield code="i">E38 1774</marc:subfield>
</marc:datafield>
<marc:datafield ind1="3" ind2="0" tag="866">
<marc:subfield code="8">0</marc:subfield>
<marc:subfield code="a">2 v.</marc:subfield>
</marc:datafield>
<marc:datafield ind1="3" ind2="0" tag="866">
<marc:subfield code="8">0</marc:subfield>
<marc:subfield code="a">(v.1-2); id=9999</marc:subfield>
</marc:datafield>
<marc:datafield ind1=" " ind2=" " tag="950">
<marc:subfield code="l">RBC</marc:subfield>
<marc:subfield code="e">\\\\\\\\Singer-\\\\Menden-\\\\hall\\\\</marc:subfield>
<marc:subfield code="v">2 v.</marc:subfield>
<marc:subfield code="i">02/25/86 C</marc:subfield>
</marc:datafield>
<marc:datafield ind1=" " ind2=" " tag="955">
<marc:subfield code="l">RBC</marc:subfield>
<marc:subfield code="c">1:(v.1-2)</marc:subfield>
<marc:subfield code="q">725378-9</marc:subfield>
<marc:subfield code="s">Ex libris: Bateman, Lady</marc:subfield>
<marc:subfield code="s">g. Mr. and Mrs. Jacob Singer</marc:subfield>
<marc:subfield code="i">02/25/86 C</marc:subfield>
</marc:datafield>
<marc:datafield ind1=" " ind2=" " tag="989">
<marc:subfield code="2">Novel</marc:subfield>
<marc:subfield code="2">Volume</marc:subfield>
<marc:subfield code="2">Permission</marc:subfield>
<marc:subfield code="2">Majesty</marc:subfield>
<marc:subfield code="3">Two</marc:subfield>
<marc:subfield code="3">Her</marc:subfield>
<marc:subfield code="5">Edward</marc:subfield>
<marc:subfield code="6">Dedicate</marc:subfield>
<marc:subfield code="v">v.1</marc:subfield>
<marc:subfield code="v">v.2</marc:subfield>
</marc:datafield>
<marc:datafield ind1=" " ind2=" " tag="999">
<marc:subfield code="a">MJR</marc:subfield>
<marc:subfield code="b">6/8/2011</marc:subfield>
<marc:subfield code="c">Swarthmore College</marc:subfield>
</marc:datafield>
</marc:record>